sisyphus/__init__.py
sisyphus/__main__.py
sisyphus/cli.py
sisyphus/conftest.py
sisyphus/agents/__init__.py
sisyphus/agents/base.py
sisyphus/agents/claude.py
sisyphus/agents/opencode.py
sisyphus/agents/tests/test_base.py
sisyphus/agents/tests/test_claude.py
sisyphus/agents/tests/test_opencode.py
sisyphus/core/__init__.py
sisyphus/core/loop.py
sisyphus/core/prompts.py
sisyphus/core/session.py
sisyphus/core/tasks.py
sisyphus/core/tests/__init__.py
sisyphus/core/tests/test_loop.py
sisyphus/core/tests/test_loop__concurrent_input_monitoring.py
sisyphus/core/tests/test_loop__execute_feedback_injection.py
sisyphus/core/tests/test_loop__integration_feedback_loop.py
sisyphus/core/tests/test_loop__non_interactive_flow.py
sisyphus/core/tests/test_loop__phase_resume.py
sisyphus/core/tests/test_loop__session_limit.py
sisyphus/core/tests/test_loop__verify_feedback_history.py
sisyphus/core/tests/test_loop__verify_phase_feedback.py
sisyphus/core/tests/test_prompts.py
sisyphus/core/tests/test_session.py
sisyphus/core/tests/test_tasks.py
sisyphus/tests/__init__.py
sisyphus/tests/test_cli.py
sisyphus/ui/__init__.py
sisyphus/ui/base.py
sisyphus/ui/themes.py
sisyphus/ui/cli/__init__.py
sisyphus/ui/cli/console.py
sisyphus/ui/tests/__init__.py
sisyphus/ui/tests/test_base.py
sisyphus/ui/tests/test_cli.py
sisyphus/ui/tests/test_tui.py
sisyphus/ui/tui/__init__.py
sisyphus/ui/tui/app.py
sisyphus/ui/tui/events.py
sisyphus/ui/tui/components/__init__.py
sisyphus/ui/tui/components/chat_log.py
sisyphus/ui/tui/components/input_bar.py
sisyphus/ui/tui/components/status_panel.py
sisyphus/ui/tui/components/tests/test_input_bar.py
sisyphus/ui/tui/layouts/__init__.py
sisyphus/ui/tui/layouts/main.py
sisyphus/utils/__init__.py
sisyphus/utils/errors.py
sisyphus/utils/logging.py
sisyphus/utils/process.py
sisyphus/utils/session_limit.py
sisyphus/utils/theme.py
sisyphus/utils/types.py
sisyphus/utils/tests/test_logging.py
sisyphus/utils/tests/test_process.py
sisyphus/utils/tests/test_types.py
sisyphus_ai-0.1.1.dist-info/METADATA
sisyphus_ai-0.1.1.dist-info/WHEEL
sisyphus_ai-0.1.1.dist-info/entry_points.txt
sisyphus_ai-0.1.1.dist-info/licenses/LICENSE.md
sisyphus_ai-0.1.1.dist-info/RECORD
