Metadata-Version: 2.4
Name: sisyphus-ai
Version: 0.1.1
Summary: Natural Language Compiler - Multi-agent orchestration system that turns your words into production-ready code
Project-URL: Homepage, https://github.com/code-yeongyu/sisyphus
Project-URL: Repository, https://github.com/code-yeongyu/sisyphus
Project-URL: Issues, https://github.com/code-yeongyu/sisyphus/issues
Project-URL: Documentation, https://github.com/code-yeongyu/sisyphus#readme
Author-email: YeonGyu-Kim <code.yeon.gyu@gmail.com>
License: Sustainable Use License 1.0
License-File: LICENSE.md
Keywords: agent,ai,automation,code-generation,compiler,llm,natural-language,orchestration
Classifier: Development Status :: 3 - Alpha
Classifier: Environment :: Console
Classifier: Intended Audience :: Developers
Classifier: Operating System :: OS Independent
Classifier: Programming Language :: Python :: 3
Classifier: Programming Language :: Python :: 3.12
Classifier: Programming Language :: Python :: 3.13
Classifier: Topic :: Scientific/Engineering :: Artificial Intelligence
Classifier: Topic :: Software Development :: Build Tools
Classifier: Topic :: Software Development :: Code Generators
Classifier: Typing :: Typed
Requires-Python: >=3.12
Requires-Dist: aiofiles>=24.0.0
Requires-Dist: anyio>=4.11.0
Requires-Dist: catppuccin>=2.5.0
Requires-Dist: claude-agent-sdk>=0.1.0
Requires-Dist: httpx>=0.28.0
Requires-Dist: rich>=13.0.0
Requires-Dist: textual>=1.0.0
Requires-Dist: trio>=0.31.0
Requires-Dist: typer>=0.15.0
Requires-Dist: uvloop>=0.21.0
